packfiles.py
packfiles-0.1.0.dist-info/METADATA
packfiles-0.1.0.dist-info/WHEEL
packfiles-0.1.0.dist-info/entry_points.txt
packfiles-0.1.0.dist-info/licenses/LICENSE
packfiles-0.1.0.dist-info/RECORD
